ffilupa/__init__.py
ffilupa/callback.py
ffilupa/compat.py
ffilupa/compile.py
ffilupa/exception.py
ffilupa/lua.pyd
ffilupa/protocol.py
ffilupa/py_from_lua.py
ffilupa/py_to_lua.py
ffilupa/runtime.py
ffilupa/util.py
ffilupa/version.txt
ffilupa-2.0.0.dist-info/DESCRIPTION.rst
ffilupa-2.0.0.dist-info/METADATA
ffilupa-2.0.0.dist-info/RECORD
ffilupa-2.0.0.dist-info/WHEEL
ffilupa-2.0.0.dist-info/metadata.json
ffilupa-2.0.0.dist-info/top_level.txt
