Metadata-Version: 2.0
Name: ffilupa
Version: 2.0.0
Summary: cffi binding of lua for python
Home-page: https://github.com/TitanSnow/ffilupa
Author: TitanSnow
Author-email: tttnns1024@gmail.com
License: LGPLv3
Platform: UNKNOWN
Classifier: Development Status :: 3 - Alpha
Classifier: Intended Audience :: Developers
Classifier: Intended Audience :: Information Technology
Classifier: License :: OSI Approved :: GNU Lesser General Public License v3 or later (LGPLv3+)
Classifier: Programming Language :: Python :: 2
Classifier: Programming Language :: Python :: 2.7
Classifier: Programming Language :: Python :: 3
Classifier: Programming Language :: Python :: 3.3
Classifier: Programming Language :: Python :: 3.4
Classifier: Programming Language :: Python :: 3.5
Classifier: Programming Language :: Python :: 3.6
Classifier: Programming Language :: Other Scripting Engines
Classifier: Operating System :: OS Independent
Classifier: Topic :: Software Development
Requires-Dist: cffi (~=1.10)
Requires-Dist: six (~=1.9)
Requires-Dist: kwonly-args (~=1.0.0)
Requires-Dist: singledispatch (~=3.4.0.3)
Requires-Dist: zope.deprecation (~=4.3)
